README.rst
setup.py
armine/__init__.py
armine/armine.py
armine/classifier.py
armine/rule.py
armine/utils.py
armine.egg-info/PKG-INFO
armine.egg-info/SOURCES.txt
armine.egg-info/dependency_links.txt
armine.egg-info/requires.txt
armine.egg-info/top_level.txt
test/test.py