Metadata-Version: 1.1
Name: armine
Version: 0.1.0
Summary: Association Rule Mining
Home-page: https://github.com/pri22296/armine
Author: Priyam Singh
Author-email: priyamsingh.22296@gmail.com
License: UNKNOWN
Download-URL: https://github.com/pri22296/armine/tarball/0.1.0
Platform: UNKNOWN
Classifier: Development Status :: 3 - Alpha
Classifier: License :: OSI Approved :: MIT License
Classifier: Programming Language :: Python
Classifier: Programming Language :: Python :: 3.5
